{
  "imports": {
    "@single-spa/welcome": "https://unpkg.com/single-spa-welcome/dist/single-spa-welcome.js",
    "react": "https://cdn.jsdelivr.net/npm/react@16.13.1/umd/react.production.min.js",
    "react-dom": "https://cdn.jsdelivr.net/npm/react-dom@16.13.1/umd/react-dom.production.min.js",
    "@mfarmer5102/root-config": "//localhost:9000/mfarmer5102-root-config.js",
    "@mfarmer5102/subOne": "https://spatest.s3.amazonaws.com/dist/mfarmer5102-subOne.js",
    "@mfarmer5102/subTwo": "//localhost:9002/mfarmer5102-subTwo.js"
  }
}